MANIFEST.in
README.md
pyproject.toml
setup.py
hydra_plugins/hydra_ray_launcher/__init__.py
hydra_plugins/hydra_ray_launcher/_config.py
hydra_plugins/hydra_ray_launcher/_core.py
hydra_plugins/hydra_ray_launcher/_core_aws.py
hydra_plugins/hydra_ray_launcher/_launcher_util.py
hydra_plugins/hydra_ray_launcher/_remote_invoke.py
hydra_plugins/hydra_ray_launcher/ray_aws_launcher.py
hydra_plugins/hydra_ray_launcher/ray_launcher.py
sadana_hydra_ray_launcher.egg-info/PKG-INFO
sadana_hydra_ray_launcher.egg-info/SOURCES.txt
sadana_hydra_ray_launcher.egg-info/dependency_links.txt
sadana_hydra_ray_launcher.egg-info/requires.txt
sadana_hydra_ray_launcher.egg-info/top_level.txt