Metadata-Version: 2.1
Name: sadana-hydra-ray-launcher
Version: 1.2.0.dev1
Summary: Hydra Ray launcher plugin
Home-page: https://github.com/facebookresearch/hydra/
Author: Jieru Hu
Author-email: jieru@fb.com
License: UNKNOWN
Platform: UNKNOWN
Classifier: License :: OSI Approved :: MIT License
Classifier: Programming Language :: Python :: 3.7
Classifier: Programming Language :: Python :: 3.8
Classifier: Operating System :: MacOS
Classifier: Operating System :: POSIX :: Linux
